tomlhold/__init__.py
tomlhold/core/__init__.py
tomlhold/tests/__init__.py
tomlhold/tests/test_core.py
tomlhold/tests/test_mix.py
tomlhold/tests/test_types.py
tomlhold-1.1.8.dist-info/licenses/LICENSE.txt
tomlhold-1.1.8.dist-info/METADATA
tomlhold-1.1.8.dist-info/WHEEL
tomlhold-1.1.8.dist-info/top_level.txt
tomlhold-1.1.8.dist-info/RECORD
