Metadata-Version: 2.4
Name: tomlhold
Version: 1.1.8
Summary: This project provides holders for TOML data.
Author-email: Johannes <johannes.programming@gmail.com>
License: The MIT License (MIT)
Project-URL: Download, https://pypi.org/project/tomlhold/#files
Project-URL: Index, https://pypi.org/project/tomlhold/
Project-URL: Source, https://github.com/johannes-programming/tomlhold/
Project-URL: Website, https://tomlhold.johannes-programming.online/
Classifier: Development Status :: 5 - Production/Stable
Classifier: Intended Audience :: Developers
Classifier: License :: OSI Approved :: MIT License
Classifier: Natural Language :: English
Classifier: Operating System :: OS Independent
Classifier: Programming Language :: Python
Classifier: Programming Language :: Python :: 3
Classifier: Programming Language :: Python :: 3 :: Only
Classifier: Typing :: Typed
Requires-Python: >=3.11
License-File: LICENSE.txt
Requires-Dist: datahold<3,>=2.0
Requires-Dist: frozendict<3,>=2.4.6
Requires-Dist: setdoc<2,>=1.2.6
Requires-Dist: tomli-w<2,>=1.0
Dynamic: license-file
